Metadata-Version: 1.0
Name: montage
Version: 0.3.6
Summary: photogallery using decoupage
Home-page: http://k0s.org/hg/montage
Author: Jeff Hammel
Author-email: k0scist@gmail.com
License: GPL
Keywords: photo gallery decoupage
Platform: UNKNOWN
